Workbook

Sheet Start Here
B2: Cayman Islands Relocation Financial Model
B3: Built by Seb Nehme Consultancy — sebnehmeconsultancy.example
B5: How to use this model
B7: 1. Go to the "Inputs" tab and enter your annual income, home country, and household details (blue cells only).
B8: 2. The "Tax & Cost Model" tab automatically calculates your estimated home-country tax, Cayman tax (0%), and monthly cost of living.
B9: 3. The "10-Year Projection" tab shows what those annual savings could grow into over a decade, both unreinvested and reinvested at a hypothetical rate you control.
B10: 4. Change any blue input cell and every formula in the workbook updates automatically.
B12: Important disclaimer
B13: This model uses approximate top marginal tax rates and general market data for illustrative purposes only. It does not account for citizenship-based taxation (U.S.), exit taxes, deductions, treaties, deductions, or your specific financial structure. It is not tax, legal, or financial advice. Talk to Seb and a licensed professional before making any decisions.
B15: Questions about your specific numbers? Message Seb directly on WhatsApp: https://wa.me/13455550134

Sheet Inputs
B2: Your Inputs | D2: Edit the blue cells. Everything else updates automatically.
B5: Annual Income (USD) | C5: 250000 | D5: Your current gross annual income.
B6: Home Country Marginal Tax Rate | C6: 0.42 | D6: Approximate top marginal rate: US 42%, Canada 53%, UK 47%, Other 40% (edit if you know your actual rate).
B7: Household Size | C7: 2 | D7: 1 = just you, 2 = couple, 4 = family of four (used for cost-of-living estimate).
B8: Est. Monthly Housing (USD) | C8: 4500 | D8: Modern condo ~3,200 / Beachfront villa ~4,500 / Luxury estate ~9,000.
B9: Est. Monthly Living Expenses (USD) | C9: 2800 | D9: Groceries, utilities, transport, dining — scales with household size.
B10: One-Time Company Setup Cost (USD) | C10: 4500 | D10: Typical Cayman exempted company formation + first-year registered office/agent fees.
B11: Reinvestment Growth Rate (Hypothetical) | C11: 0.07 | D11: Hypothetical average annual return if annual tax savings were reinvested. Not a projection or guarantee.
B12: Projection Horizon (Years) | C12: 10 | D12: How many years forward to project.

Sheet Tax & Cost Model
B2: Tax & Cost of Living Model
B4: Tax Comparison
B5: Est. Home-Country Tax / Year | C5: =Inputs!C5*Inputs!C6 -> 105000
B6: Est. Cayman Tax / Year | C6: 0
B7: Est. Annual Tax Savings | C7: =C5-C6 -> 105000
B9: Monthly Cost of Living in Cayman
B10: Monthly Housing | C10: =Inputs!C8 -> 4500
B11: Monthly Living Expenses | C11: =Inputs!C9 -> 2800
B12: Est. Monthly Total | C12: =C10+C11 -> 7300
B13: One-Time Company Setup Cost | C13: =Inputs!C10 -> 4500
B15: Net Position
B16: Annual Tax Savings Minus Annual Cost of Living Increase* | C16: =C7-(C12*12) -> 17400 | D16: *Illustrative only — assumes your Cayman cost of living is fully incremental; your actual comparison should net out what you already spend at home.

Sheet 10-Year Projection
B2: 10-Year Wealth Impact Projection
B3: Hypothetical illustration only. Assumes constant annual tax savings and, in the "Reinvested" column, a constant hypothetical annual return. Not a guarantee or investment advice.
B5: Year | C5: Annual Savings | D5: Cumulative (Not Invested) | E5: Cumulative (Reinvested)
B6: 1 | C6: ='Tax & Cost Model'!C7 -> 105000 | D6: =C6 -> 105000 | E6: =C6 -> 105000
B7: 2 | C7: ='Tax & Cost Model'!C7 -> 105000 | D7: =D6+C7 -> 210000 | E7: =E6*(1+Inputs!C11)+C7 -> 217350
B8: 3 | C8: ='Tax & Cost Model'!C7 -> 105000 | D8: =D7+C8 -> 315000 | E8: =E7*(1+Inputs!C11)+C8 -> 337564.5
B9: 4 | C9: ='Tax & Cost Model'!C7 -> 105000 | D9: =D8+C9 -> 420000 | E9: =E8*(1+Inputs!C11)+C9 -> 466194.02
B10: 5 | C10: ='Tax & Cost Model'!C7 -> 105000 | D10: =D9+C10 -> 525000 | E10: =E9*(1+Inputs!C11)+C10 -> 603827.6
B11: 6 | C11: ='Tax & Cost Model'!C7 -> 105000 | D11: =D10+C11 -> 630000 | E11: =E10*(1+Inputs!C11)+C11 -> 751095.53
B12: 7 | C12: ='Tax & Cost Model'!C7 -> 105000 | D12: =D11+C12 -> 735000 | E12: =E11*(1+Inputs!C11)+C12 -> 908672.21
B13: 8 | C13: ='Tax & Cost Model'!C7 -> 105000 | D13: =D12+C13 -> 840000 | E13: =E12*(1+Inputs!C11)+C13 -> 1077279.3
B14: 9 | C14: ='Tax & Cost Model'!C7 -> 105000 | D14: =D13+C14 -> 945000 | E14: =E13*(1+Inputs!C11)+C14 -> 1257688.8
B15: 10 | C15: ='Tax & Cost Model'!C7 -> 105000 | D15: =D14+C15 -> 1050000 | E15: =E14*(1+Inputs!C11)+C15 -> 1450727
B17: Total After 10 Years | D17: =D15 -> 1050000 | E17: =E15 -> 1450727
